audial/__init__.py
audial/api/__init__.py
audial/api/auth.py
audial/api/constants.py
audial/api/exceptions.py
audial/api/proxy.py
audial/cli/__init__.py
audial/cli/commands.py
audial/functions/__init__.py
audial/functions/analyze.py
audial/functions/master.py
audial/functions/midi.py
audial/functions/samples.py
audial/functions/segment.py
audial/functions/stem_split.py
audial/utils/__init__.py
audial/utils/config.py
audial/utils/file_utils.py
audial/utils/results_manager.py
audial_sdk-1.0.1.dist-info/licenses/LICENSE
audial_sdk-1.0.1.dist-info/METADATA
audial_sdk-1.0.1.dist-info/WHEEL
audial_sdk-1.0.1.dist-info/entry_points.txt
audial_sdk-1.0.1.dist-info/top_level.txt
audial_sdk-1.0.1.dist-info/RECORD
