Metadata-Version: 2.4
Name: audial-sdk
Version: 1.0.1
Summary: Python SDK for the Audial audio processing API
Home-page: https://github.com/audial/audial-sdk
Author: Audial Team
Author-email: support@audial.io
Project-URL: Bug Tracker, https://github.com/audial/audial-sdk/issues
Project-URL: Documentation, https://github.com/audial/audial-sdk/blob/main/API_DOCUMENTATION.md
Classifier: Development Status :: 5 - Production/Stable
Classifier: Intended Audience :: Developers
Classifier: Topic :: Multimedia :: Sound/Audio
Classifier: Programming Language :: Python :: 3
Classifier: Programming Language :: Python :: 3.7
Classifier: Programming Language :: Python :: 3.8
Classifier: Programming Language :: Python :: 3.9
Classifier: Programming Language :: Python :: 3.10
Classifier: Programming Language :: Python :: 3.11
Classifier: Programming Language :: Python :: 3.12
Classifier: License :: OSI Approved :: MIT License
Classifier: Operating System :: OS Independent
Requires-Python: >=3.7
License-File: LICENSE
Requires-Dist: requests>=2.25.0
Requires-Dist: tqdm>=4.62.0
Requires-Dist: python-dotenv>=0.19.0
Requires-Dist: click>=8.0.0
Requires-Dist: importlib-metadata>=1.0.0; python_version < "3.8"
Requires-Dist: pytest>=6.0.0
Requires-Dist: pytest-cov>=2.12.0
Requires-Dist: pytest-mock>=3.6.0
Requires-Dist: black>=21.5b2
Requires-Dist: flake8>=3.9.0
Dynamic: author
Dynamic: author-email
Dynamic: classifier
Dynamic: description
Dynamic: description-content-type
Dynamic: home-page
Dynamic: license-file
Dynamic: project-url
Dynamic: requires-dist
Dynamic: requires-python
Dynamic: summary
